git_improved/__init__.py
git_improved/changelog.py
git_improved/command.py
git_improved/configurations.py
git_improved/constants.py
git_improved/exceptions.py
git_improved/git.py
git_improved/menu.py
git_improved/shell.py
git_improved/template.py
git_improved/commands/__init__.py
git_improved/commands/cancel.py
git_improved/commands/done.py
git_improved/commands/release.py
git_improved/commands/save.py
git_improved/commands/setup.py
git_improved/commands/template.py
git_improved/commands/unrelease.py
git_improved/commands/wip.py
git_improved/templates/__init__.py
git_improved/templates/python_package.py
git_improved-0.1.5.dist-info/METADATA
git_improved-0.1.5.dist-info/WHEEL
git_improved-0.1.5.dist-info/entry_points.txt
git_improved-0.1.5.dist-info/top_level.txt
git_improved-0.1.5.dist-info/RECORD
