Metadata-Version: 2.1
Name: git-improved
Version: 0.1.5
Summary: Add commands to simplify release and publish operation from Git CLI.
Home-page: UNKNOWN
License: UNKNOWN
Platform: UNKNOWN
Requires-Dist: bump2version
Requires-Dist: jinja2
Requires-Dist: requests
